testcompose/__init__.py
testcompose/client/__init__.py
testcompose/client/base_docker_client.py
testcompose/configs/__init__.py
testcompose/configs/config_templates.py
testcompose/configs/generate_template_config.py
testcompose/configs/parse_config.py
testcompose/configs/service_config.py
testcompose/configs/template_cmd.py
testcompose/containers/__init__.py
testcompose/containers/base_container.py
testcompose/containers/clean_up_container.py
testcompose/containers/container_network.py
testcompose/containers/container_utils.py
testcompose/containers/generic_container.py
testcompose/housekeeping/__init__.py
testcompose/housekeeping/clean_up_container.py
testcompose/log_setup.py
testcompose/models/__init__.py
testcompose/models/bootstrap/__init__.py
testcompose/models/bootstrap/container_http_wait_parameter.py
testcompose/models/bootstrap/container_log_wait_parameter.py
testcompose/models/bootstrap/container_service.py
testcompose/models/bootstrap/container_volume.py
testcompose/models/client/__init__.py
testcompose/models/client/client_login.py
testcompose/models/client/registry_parameters.py
testcompose/models/container/__init__.py
testcompose/models/container/running_container.py
testcompose/models/container/running_container_attributes.py
testcompose/models/container/supported_placeholders.py
testcompose/models/network/__init__.py
testcompose/models/network/network.py
testcompose/run_containers.py
testcompose/testcompose.py
testcompose/waiters/__init__.py
testcompose/waiters/endpoint_waiters.py
testcompose/waiters/log_waiters.py
testcompose/waiters/waiting_utils.py
testcompose-0.2.1.dist-info/LICENSE
testcompose-0.2.1.dist-info/METADATA
testcompose-0.2.1.dist-info/WHEEL
testcompose-0.2.1.dist-info/entry_points.txt
testcompose-0.2.1.dist-info/RECORD
