Metadata-Version: 2.1
Name: testcompose
Version: 0.2.1
Summary: Provide an easy way to perform integration testing with docker and python
License: MIT
Keywords: docker,testcontainers
Author: Olakunle Olaniyi
Author-email: rugging24@gmail.com
Maintainer: Olakunle Olaniyi
Maintainer-email: rugging24@gmail.com
Requires-Python: >=3.7,<4.0
Classifier: Environment :: Console
Classifier: Intended Audience :: Developers
Classifier: Intended Audience :: Information Technology
Classifier: Intended Audience :: System Administrators
Classifier: License :: OSI Approved :: Apache Software License
Classifier: License :: OSI Approved :: MIT License
Classifier: Programming Language :: Python :: 3
Classifier: Programming Language :: Python :: 3.7
Classifier: Programming Language :: Python :: 3.8
Classifier: Programming Language :: Python :: 3.9
Classifier: Programming Language :: Python :: 3.10
Classifier: Programming Language :: Python :: 3.11
Classifier: Topic :: Software Development :: Libraries :: Python Modules
Classifier: Topic :: Software Development :: Testing
Requires-Dist: PyYAML (==6.0.1)
Requires-Dist: click (>=8.1.3,<9.0.0)
Requires-Dist: docker (>=6.1.3,<7.0.0)
Requires-Dist: pydantic (<2.0.0)
Requires-Dist: requests (>=2.31.0,<3.0.0)
